simple_calc/__init__.py
simple_calc/operations.py
simple_calc_pkg-0.1.0.dist-info/licenses/LICENSE
simple_calc_pkg-0.1.0.dist-info/METADATA
simple_calc_pkg-0.1.0.dist-info/WHEEL
simple_calc_pkg-0.1.0.dist-info/top_level.txt
simple_calc_pkg-0.1.0.dist-info/RECORD
