Metadata-Version: 2.4
Name: simple-calc-pkg
Version: 0.1.0
Summary: A sample calculator package with add/subtract/multiply/divide.
Author-email: Ch Srinivasa Rao <airobohub@gmail.com>
License: MIT
Requires-Python: >=3.8
License-File: LICENSE
Dynamic: license-file
